<annotation>
	<folder>images</folder>
	<filename>photo_104.jpg</filename>
	<path>/Users/jamesc/src/object_following/data/training/images/photo_104.jpg</path>
	<source>
		<database>Unknown</database>
	</source>
	<size>
		<width>960</width>
		<height>1280</height>
		<depth>3</depth>
	</size>
	<segmented>0</segmented>
	<object>
		<name>kdot</name>
		<pose>Unspecified</pose>
		<truncated>0</truncated>
		<difficult>0</difficult>
		<bndbox>
			<xmin>10</xmin>
			<ymin>170</ymin>
			<xmax>462</xmax>
			<ymax>776</ymax>
		</bndbox>
	</object>
</annotation>
