<annotation>
	<folder>images</folder>
	<filename>photo_112.jpg</filename>
	<path>/Users/jamesc/src/object_following/data/training/images/photo_112.jpg</path>
	<source>
		<database>Unknown</database>
	</source>
	<size>
		<width>3024</width>
		<height>4032</height>
		<depth>3</depth>
	</size>
	<segmented>0</segmented>
	<object>
		<name>kdot</name>
		<pose>Unspecified</pose>
		<truncated>0</truncated>
		<difficult>0</difficult>
		<bndbox>
			<xmin>1167</xmin>
			<ymin>11</ymin>
			<xmax>2202</xmax>
			<ymax>1036</ymax>
		</bndbox>
	</object>
	<object>
		<name>bella</name>
		<pose>Unspecified</pose>
		<truncated>0</truncated>
		<difficult>0</difficult>
		<bndbox>
			<xmin>1852</xmin>
			<ymin>2596</ymin>
			<xmax>2482</xmax>
			<ymax>3401</ymax>
		</bndbox>
	</object>
</annotation>
